LICENSE.txt
README.rst
setup.py
itproject/__init__.py
itproject/deeplearning/LinearModel.py
itproject/deeplearning/__init__.py
itproject/machinelearning/KNN.py
itproject/machinelearning/KNNRegressor.py
itproject/machinelearning/__init__.py
itproject/mathbasic/MatrixUtil.py
itproject/mathbasic/__init__.py
itproject/utils/AnalyseUtil.py
itproject/utils/ArrayUtil.py
itproject/utils/ChartUtil.py
itproject/utils/DataUtil.py
itproject/utils/SerializeUtil.py
itproject/utils/TensorUtil.py
itproject/utils/__init__.py
itprojectai.egg-info/PKG-INFO
itprojectai.egg-info/SOURCES.txt
itprojectai.egg-info/dependency_links.txt
itprojectai.egg-info/requires.txt
itprojectai.egg-info/top_level.txt